case_attribute_discovery/__init__.py
case_attribute_discovery/config.py
case_attribute_discovery/discovery.py
case_attribute_discovery-0.1.8.dist-info/LICENSE
case_attribute_discovery-0.1.8.dist-info/METADATA
case_attribute_discovery-0.1.8.dist-info/WHEEL
case_attribute_discovery-0.1.8.dist-info/RECORD
