Metadata-Version: 2.1
Name: case-attribute-discovery
Version: 0.1.8
Summary: 
Author: David Chapela de la Campa
Author-email: david.chapela.delacampa@gmail.com
Requires-Python: >=3.9,<3.12
Classifier: Programming Language :: Python :: 3
Classifier: Programming Language :: Python :: 3.9
Classifier: Programming Language :: Python :: 3.10
Classifier: Programming Language :: Python :: 3.11
Requires-Dist: pandas (>=2.0.2,<3.0.0)
Requires-Dist: pix-framework (>=0.10.0,<0.11.0)
Requires-Dist: setuptools (>=67.8.0,<68.0.0)
